grapeshot_signal/__init__.py
grapeshot_signal/client.py
grapeshot_signal/config.py
grapeshot_signal/errors.py
grapeshot_signal/model.py
grapeshot_signal/rels.py
grapeshot_signal_sdk-0.0a2.dist-info/DESCRIPTION.rst
grapeshot_signal_sdk-0.0a2.dist-info/METADATA
grapeshot_signal_sdk-0.0a2.dist-info/RECORD
grapeshot_signal_sdk-0.0a2.dist-info/WHEEL
grapeshot_signal_sdk-0.0a2.dist-info/metadata.json
grapeshot_signal_sdk-0.0a2.dist-info/top_level.txt
